{"box_data": [{"position": {"minX": 339.25, "minY": 214.25, "maxX": 361.25, "maxY": 248.75}, "class_id": 0, "box_caption": "coureur 0.448", "scores": {"class_score": 0.447998046875}, "domain": "pixel"}, {"position": {"minX": 160.25, "minY": 196.25, "maxX": 184.5, "maxY": 221.75}, "class_id": 0, "box_caption": "coureur 0.431", "scores": {"class_score": 0.4306640625}, "domain": "pixel"}, {"position": {"minX": 291.25, "minY": 211.5, "maxX": 310.25, "maxY": 237.25}, "class_id": 0, "box_caption": "coureur 0.425", "scores": {"class_score": 0.42529296875}, "domain": "pixel"}, {"position": {"minX": 578.5, "minY": 249.875, "maxX": 603.5, "maxY": 277.25}, "class_id": 0, "box_caption": "coureur 0.423", "scores": {"class_score": 0.422607421875}, "domain": "pixel"}, {"position": {"minX": 222.625, "minY": 199.5, "maxX": 242.875, "maxY": 227.25}, "class_id": 0, "box_caption": "coureur 0.420", "scores": {"class_score": 0.42041015625}, "domain": "pixel"}, {"position": {"minX": 451.25, "minY": 232.75, "maxX": 474.25, "maxY": 263.25}, "class_id": 0, "box_caption": "coureur 0.413", "scores": {"class_score": 0.41259765625}, "domain": "pixel"}, {"position": {"minX": 393.25, "minY": 233.25, "maxX": 404.25, "maxY": 253.0}, "class_id": 0, "box_caption": "coureur 0.387", "scores": {"class_score": 0.387451171875}, "domain": "pixel"}, {"position": {"minX": 528.5, "minY": 241.5, "maxX": 543.5, "maxY": 271.5}, "class_id": 0, "box_caption": "coureur 0.358", "scores": {"class_score": 0.357666015625}, "domain": "pixel"}, {"position": {"minX": 525.0, "minY": 238.25, "maxX": 541.0, "maxY": 268.0}, "class_id": 0, "box_caption": "coureur 0.005", "scores": {"class_score": 0.004955291748046875}, "domain": "pixel"}, {"position": {"minX": 530.5, "minY": 243.25, "maxX": 547.5, "maxY": 275.25}, "class_id": 0, "box_caption": "coureur 0.002", "scores": {"class_score": 0.002033233642578125}, "domain": "pixel"}, {"position": {"minX": 387.75, "minY": 232.75, "maxX": 402.25, "maxY": 255.0}, "class_id": 0, "box_caption": "coureur 0.001", "scores": {"class_score": 0.0014247894287109375}, "domain": "pixel"}], "class_labels": {"0": "coureur"}}