{
    "asset": {
        "id": "4f4e481ce8abc96b8c154f0236122ffc",
        "format": "5",
        "state": 2,
        "type": 3,
        "name": "1999-t.mp4#t=2.5",
        "path": "file:/Users/noham/Documents/GitHub/Stage/2024/VoTT/sources/1999-t.mp4#t=2.5",
        "size": {
            "width": 1920,
            "height": 1080
        },
        "parent": {
            "format": "mp4",
            "id": "f78f3ff666c27c1bcf64c8af1ea37192",
            "name": "1999-t.mp4",
            "path": "file:/Users/noham/Documents/GitHub/Stage/2024/VoTT/sources/1999-t.mp4",
            "size": {
                "width": 1920,
                "height": 1080
            },
            "state": 2,
            "type": 2
        },
        "timestamp": 2.5
    },
    "regions": [
        {
            "id": "-fbv69QHL",
            "type": "RECTANGLE",
            "tags": [
                "runner"
            ],
            "boundingBox": {
                "height": 110.8760460251046,
                "width": 50.781004709576145,
                "left": 844.1267660910519,
                "top": 934.2972018828451
            },
            "points": [
                {
                    "x": 844.1267660910519,
                    "y": 934.2972018828451
                },
                {
                    "x": 894.907770800628,
                    "y": 934.2972018828451
                },
                {
                    "x": 894.907770800628,
                    "y": 1045.1732479079496
                },
                {
                    "x": 844.1267660910519,
                    "y": 1045.1732479079496
                }
            ]
        },
        {
            "id": "Ywpm4d0Rm",
            "type": "RECTANGLE",
            "tags": [
                "runner"
            ],
            "boundingBox": {
                "height": 115.21835774058577,
                "width": 51.63461538461539,
                "left": 942.7747252747254,
                "top": 648.8578713389121
            },
            "points": [
                {
                    "x": 942.7747252747254,
                    "y": 648.8578713389121
                },
                {
                    "x": 994.4093406593407,
                    "y": 648.8578713389121
                },
                {
                    "x": 994.4093406593407,
                    "y": 764.0762290794979
                },
                {
                    "x": 942.7747252747254,
                    "y": 764.0762290794979
                }
            ]
        },
        {
            "id": "wbgEMRe2T",
            "type": "RECTANGLE",
            "tags": [
                "runner"
            ],
            "boundingBox": {
                "height": 78.2557531380753,
                "width": 52.411695447409734,
                "left": 945.2354788069074,
                "top": 446.65206589958154
            },
            "points": [
                {
                    "x": 945.2354788069074,
                    "y": 446.65206589958154
                },
                {
                    "x": 997.6471742543172,
                    "y": 446.65206589958154
                },
                {
                    "x": 997.6471742543172,
                    "y": 524.9078190376569
                },
                {
                    "x": 945.2354788069074,
                    "y": 524.9078190376569
                }
            ]
        },
        {
            "id": "LH5hgjvbB",
            "type": "RECTANGLE",
            "tags": [
                "runner"
            ],
            "boundingBox": {
                "height": 80.19743723849372,
                "width": 52.40580847723705,
                "left": 893.3300627943486,
                "top": 299.01935146443515
            },
            "points": [
                {
                    "x": 893.3300627943486,
                    "y": 299.01935146443515
                },
                {
                    "x": 945.7358712715857,
                    "y": 299.01935146443515
                },
                {
                    "x": 945.7358712715857,
                    "y": 379.21678870292885
                },
                {
                    "x": 893.3300627943486,
                    "y": 379.21678870292885
                }
            ]
        },
        {
            "id": "HROQrp-Zm",
            "type": "RECTANGLE",
            "tags": [
                "runner"
            ],
            "boundingBox": {
                "height": 47.71247384937238,
                "width": 44.25824175824176,
                "left": 811.9368131868132,
                "top": 199.4639121338912
            },
            "points": [
                {
                    "x": 811.9368131868132,
                    "y": 199.4639121338912
                },
                {
                    "x": 856.195054945055,
                    "y": 199.4639121338912
                },
                {
                    "x": 856.195054945055,
                    "y": 247.1763859832636
                },
                {
                    "x": 811.9368131868132,
                    "y": 247.1763859832636
                }
            ]
        },
        {
            "id": "WKrbKXj93",
            "type": "RECTANGLE",
            "tags": [
                "runner"
            ],
            "boundingBox": {
                "height": 54.15533472803347,
                "width": 39.21899529042386,
                "left": 724.291601255887,
                "top": 109.24620815899581
            },
            "points": [
                {
                    "x": 724.291601255887,
                    "y": 109.24620815899581
                },
                {
                    "x": 763.5105965463109,
                    "y": 109.24620815899581
                },
                {
                    "x": 763.5105965463109,
                    "y": 163.40154288702928
                },
                {
                    "x": 724.291601255887,
                    "y": 163.40154288702928
                }
            ]
        },
        {
            "id": "AyT7JjGfr",
            "type": "RECTANGLE",
            "tags": [
                "runner"
            ],
            "boundingBox": {
                "height": 51.10747907949791,
                "width": 57.39207221350079,
                "left": 612.2154631083203,
                "top": 56.19704497907949
            },
            "points": [
                {
                    "x": 612.2154631083203,
                    "y": 56.19704497907949
                },
                {
                    "x": 669.607535321821,
                    "y": 56.19704497907949
                },
                {
                    "x": 669.607535321821,
                    "y": 107.3045240585774
                },
                {
                    "x": 612.2154631083203,
                    "y": 107.3045240585774
                }
            ]
        },
        {
            "id": "pAowowPqR",
            "type": "RECTANGLE",
            "tags": [
                "runner"
            ],
            "boundingBox": {
                "height": 35.67991631799163,
                "width": 62.431318681318686,
                "left": 493.1102825745683,
                "top": 22.15873430962343
            },
            "points": [
                {
                    "x": 493.1102825745683,
                    "y": 22.15873430962343
                },
                {
                    "x": 555.541601255887,
                    "y": 22.15873430962343
                },
                {
                    "x": 555.541601255887,
                    "y": 57.83865062761506
                },
                {
                    "x": 493.1102825745683,
                    "y": 57.83865062761506
                }
            ]
        }
    ],
    "version": "2.2.0"
}