{
    "asset": {
        "id": "a1ec07fa865c099fd6f9dca700a8c074",
        "format": "5",
        "state": 2,
        "type": 3,
        "name": "1999-t.mp4#t=26.5",
        "path": "file:/Users/noham/Documents/GitHub/Stage/2024/VoTT/sources/1999-t.mp4#t=26.5",
        "size": {
            "width": 1920,
            "height": 1080
        },
        "parent": {
            "format": "mp4",
            "id": "f78f3ff666c27c1bcf64c8af1ea37192",
            "name": "1999-t.mp4",
            "path": "file:/Users/noham/Documents/GitHub/Stage/2024/VoTT/sources/1999-t.mp4",
            "size": {
                "width": 1920,
                "height": 1080
            },
            "state": 2,
            "type": 2
        },
        "timestamp": 26.5
    },
    "regions": [
        {
            "id": "SoP8cZpr0",
            "type": "RECTANGLE",
            "tags": [
                "runner"
            ],
            "boundingBox": {
                "height": 83.9984309623431,
                "width": 38.45957613814757,
                "left": 524.3229984301413,
                "top": 531.5448483263598
            },
            "points": [
                {
                    "x": 524.3229984301413,
                    "y": 531.5448483263598
                },
                {
                    "x": 562.7825745682889,
                    "y": 531.5448483263598
                },
                {
                    "x": 562.7825745682889,
                    "y": 615.5432792887029
                },
                {
                    "x": 524.3229984301413,
                    "y": 615.5432792887029
                }
            ]
        },
        {
            "id": "NbGTfg5oA",
            "type": "RECTANGLE",
            "tags": [
                "runner"
            ],
            "boundingBox": {
                "height": 79.83851987447699,
                "width": 32.24293563579287,
                "left": 586.2480376766091,
                "top": 537.5640690376569
            },
            "points": [
                {
                    "x": 586.2480376766091,
                    "y": 537.5640690376569
                },
                {
                    "x": 618.490973312402,
                    "y": 537.5640690376569
                },
                {
                    "x": 618.490973312402,
                    "y": 617.4025889121338
                },
                {
                    "x": 586.2480376766091,
                    "y": 617.4025889121338
                }
            ]
        },
        {
            "id": "FoSf5kh2F",
            "type": "RECTANGLE",
            "tags": [
                "runner"
            ],
            "boundingBox": {
                "height": 78.22044979079497,
                "width": 35.73979591836735,
                "left": 772.9003139717425,
                "top": 505.4615585774058
            },
            "points": [
                {
                    "x": 772.9003139717425,
                    "y": 505.4615585774058
                },
                {
                    "x": 808.6401098901099,
                    "y": 505.4615585774058
                },
                {
                    "x": 808.6401098901099,
                    "y": 583.6820083682009
                },
                {
                    "x": 772.9003139717425,
                    "y": 583.6820083682009
                }
            ]
        },
        {
            "id": "R_N-vT6qc",
            "type": "RECTANGLE",
            "tags": [
                "runner"
            ],
            "boundingBox": {
                "height": 77.69089958158996,
                "width": 35.710361067503925,
                "left": 853.2986656200942,
                "top": 510.7688284518828
            },
            "points": [
                {
                    "x": 853.2986656200942,
                    "y": 510.7688284518828
                },
                {
                    "x": 889.0090266875982,
                    "y": 510.7688284518828
                },
                {
                    "x": 889.0090266875982,
                    "y": 588.4597280334727
                },
                {
                    "x": 853.2986656200942,
                    "y": 588.4597280334727
                }
            ]
        },
        {
            "id": "vGlRSHK6H",
            "type": "RECTANGLE",
            "tags": [
                "runner"
            ],
            "boundingBox": {
                "height": 74.7489539748954,
                "width": 45.606357927786505,
                "left": 1025.9811616954476,
                "top": 489.4573744769874
            },
            "points": [
                {
                    "x": 1025.9811616954476,
                    "y": 489.4573744769874
                },
                {
                    "x": 1071.587519623234,
                    "y": 489.4573744769874
                },
                {
                    "x": 1071.587519623234,
                    "y": 564.2063284518828
                },
                {
                    "x": 1025.9811616954476,
                    "y": 564.2063284518828
                }
            ]
        },
        {
            "id": "WMTKn7h_2",
            "type": "RECTANGLE",
            "tags": [
                "runner"
            ],
            "boundingBox": {
                "height": 79.05596234309623,
                "width": 44.49372056514914,
                "left": 1167.427394034537,
                "top": 482.40847280334725
            },
            "points": [
                {
                    "x": 1167.427394034537,
                    "y": 482.40847280334725
                },
                {
                    "x": 1211.921114599686,
                    "y": 482.40847280334725
                },
                {
                    "x": 1211.921114599686,
                    "y": 561.4644351464435
                },
                {
                    "x": 1167.427394034537,
                    "y": 561.4644351464435
                }
            ]
        },
        {
            "id": "RJHVCQGo-",
            "type": "RECTANGLE",
            "tags": [
                "runner"
            ],
            "boundingBox": {
                "height": 86.93449267782427,
                "width": 50.021585557299844,
                "left": 1322.7963108320253,
                "top": 466.29837866108784
            },
            "points": [
                {
                    "x": 1322.7963108320253,
                    "y": 466.29837866108784
                },
                {
                    "x": 1372.8178963893251,
                    "y": 466.29837866108784
                },
                {
                    "x": 1372.8178963893251,
                    "y": 553.2328713389121
                },
                {
                    "x": 1322.7963108320253,
                    "y": 553.2328713389121
                }
            ]
        },
        {
            "id": "o48rhsLpI",
            "type": "RECTANGLE",
            "tags": [
                "runner"
            ],
            "boundingBox": {
                "height": 67.41174163179916,
                "width": 55.272762951334556,
                "left": 1482.9513343799058,
                "top": 468.8225679916318
            },
            "points": [
                {
                    "x": 1482.9513343799058,
                    "y": 468.8225679916318
                },
                {
                    "x": 1538.2240973312405,
                    "y": 468.8225679916318
                },
                {
                    "x": 1538.2240973312405,
                    "y": 536.2343096234309
                },
                {
                    "x": 1482.9513343799058,
                    "y": 536.2343096234309
                }
            ]
        },
        {
            "id": "Alsm5gYkg",
            "type": "RECTANGLE",
            "tags": [
                "runner"
            ],
            "boundingBox": {
                "height": 72.5777981171549,
                "width": 38.36538461538462,
                "left": 1585.4317111459973,
                "top": 472.69416841004175
            },
            "points": [
                {
                    "x": 1585.4317111459973,
                    "y": 472.69416841004175
                },
                {
                    "x": 1623.797095761382,
                    "y": 472.69416841004175
                },
                {
                    "x": 1623.797095761382,
                    "y": 545.2719665271966
                },
                {
                    "x": 1585.4317111459973,
                    "y": 545.2719665271966
                }
            ]
        }
    ],
    "version": "2.2.0"
}