{
    "asset": {
        "id": "21014667e343614518f5542174e7a4b6",
        "format": "mp4",
        "state": 2,
        "type": 3,
        "name": "2016-100m.mp4#t=8",
        "path": "file:/Users/noham/Documents/GitHub/Stage-2024/VoTT-v2/sources/2016-100m.mp4#t=8",
        "size": {
            "width": 1920,
            "height": 1080
        },
        "parent": {
            "format": "mp4",
            "id": "de3cf5a63a6a4305ba57b9399747b316",
            "name": "2016-100m.mp4",
            "path": "file:/Users/noham/Documents/GitHub/Stage-2024/VoTT-v2/sources/2016-100m.mp4",
            "size": {
                "width": 1920,
                "height": 1080
            },
            "state": 1,
            "type": 2
        },
        "timestamp": 8
    },
    "regions": [
        {
            "id": "1JHFbAitN",
            "type": "RECTANGLE",
            "tags": [
                "runner"
            ],
            "boundingBox": {
                "height": 342.25790513833994,
                "width": 173.73333333333335,
                "left": 291.2277777777778,
                "top": 407.3900691699605
            },
            "points": [
                {
                    "x": 291.2277777777778,
                    "y": 407.3900691699605
                },
                {
                    "x": 464.9611111111111,
                    "y": 407.3900691699605
                },
                {
                    "x": 464.9611111111111,
                    "y": 749.6479743083004
                },
                {
                    "x": 291.2277777777778,
                    "y": 749.6479743083004
                }
            ]
        },
        {
            "id": "qv__eG5YP",
            "type": "RECTANGLE",
            "tags": [
                "runner"
            ],
            "boundingBox": {
                "height": 352.0905385375495,
                "width": 138.01111111111112,
                "left": 563.2,
                "top": 378.542490118577
            },
            "points": [
                {
                    "x": 563.2,
                    "y": 378.542490118577
                },
                {
                    "x": 701.2111111111111,
                    "y": 378.542490118577
                },
                {
                    "x": 701.2111111111111,
                    "y": 730.6330286561265
                },
                {
                    "x": 563.2,
                    "y": 730.6330286561265
                }
            ]
        },
        {
            "id": "VRCvpEbty",
            "type": "RECTANGLE",
            "tags": [
                "runner"
            ],
            "boundingBox": {
                "height": 325.838685770751,
                "width": 145.7111111111111,
                "left": 713.9277777777778,
                "top": 352.3351037549407
            },
            "points": [
                {
                    "x": 713.9277777777778,
                    "y": 352.3351037549407
                },
                {
                    "x": 859.6388888888889,
                    "y": 352.3351037549407
                },
                {
                    "x": 859.6388888888889,
                    "y": 678.1737895256917
                },
                {
                    "x": 713.9277777777778,
                    "y": 678.1737895256917
                }
            ]
        },
        {
            "id": "ORU6WRFpT",
            "type": "RECTANGLE",
            "tags": [
                "runner"
            ],
            "boundingBox": {
                "height": 388.86981225296444,
                "width": 129.3111111111111,
                "left": 953.0611111111111,
                "top": 302.6716897233202
            },
            "points": [
                {
                    "x": 953.0611111111111,
                    "y": 302.6716897233202
                },
                {
                    "x": 1082.3722222222223,
                    "y": 302.6716897233202
                },
                {
                    "x": 1082.3722222222223,
                    "y": 691.5415019762846
                },
                {
                    "x": 953.0611111111111,
                    "y": 691.5415019762846
                }
            ]
        },
        {
            "id": "eTukN57_B",
            "type": "RECTANGLE",
            "tags": [
                "runner"
            ],
            "boundingBox": {
                "height": 288.05891798418975,
                "width": 130.45000000000002,
                "left": 1040.7,
                "top": 275.8695652173913
            },
            "points": [
                {
                    "x": 1040.7,
                    "y": 275.8695652173913
                },
                {
                    "x": 1171.15,
                    "y": 275.8695652173913
                },
                {
                    "x": 1171.15,
                    "y": 563.928483201581
                },
                {
                    "x": 1040.7,
                    "y": 563.928483201581
                }
            ]
        },
        {
            "id": "TEyGA01hE",
            "type": "RECTANGLE",
            "tags": [
                "runner"
            ],
            "boundingBox": {
                "height": 343.55854743083006,
                "width": 132.21666666666667,
                "left": 1368.177777777778,
                "top": 293.93959980237156
            },
            "points": [
                {
                    "x": 1368.177777777778,
                    "y": 293.93959980237156
                },
                {
                    "x": 1500.3944444444444,
                    "y": 293.93959980237156
                },
                {
                    "x": 1500.3944444444444,
                    "y": 637.4981472332016
                },
                {
                    "x": 1368.177777777778,
                    "y": 637.4981472332016
                }
            ]
        },
        {
            "id": "5zcOcOlmW",
            "type": "RECTANGLE",
            "tags": [
                "runner"
            ],
            "boundingBox": {
                "height": 331.0023468379447,
                "width": 110.00555555555556,
                "left": 1478.5833333333335,
                "top": 247.52223320158103
            },
            "points": [
                {
                    "x": 1478.5833333333335,
                    "y": 247.52223320158103
                },
                {
                    "x": 1588.588888888889,
                    "y": 247.52223320158103
                },
                {
                    "x": 1588.588888888889,
                    "y": 578.5245800395257
                },
                {
                    "x": 1478.5833333333335,
                    "y": 578.5245800395257
                }
            ]
        },
        {
            "id": "alVG91GK1",
            "type": "RECTANGLE",
            "tags": [
                "runner"
            ],
            "boundingBox": {
                "height": 328.79014328063244,
                "width": 136.73333333333335,
                "left": 1612.0111111111112,
                "top": 220.88129940711462
            },
            "points": [
                {
                    "x": 1612.0111111111112,
                    "y": 220.88129940711462
                },
                {
                    "x": 1748.7444444444445,
                    "y": 220.88129940711462
                },
                {
                    "x": 1748.7444444444445,
                    "y": 549.671442687747
                },
                {
                    "x": 1612.0111111111112,
                    "y": 549.671442687747
                }
            ]
        }
    ],
    "version": "2.2.0"
}