{
    "asset": {
        "id": "3ea16d2714fc3bb94e9ccb385e77243e",
        "format": "mp4",
        "state": 2,
        "type": 3,
        "name": "2023-100m.mp4#t=0",
        "path": "file:/Users/noham/Documents/GitHub/Stage-2024/VoTT-v2/sources/2023-100m.mp4#t=0",
        "size": {
            "width": 1920,
            "height": 1080
        },
        "parent": {
            "format": "mp4",
            "id": "251d8f89412ff6d9a8826a2aac389529",
            "name": "2023-100m.mp4",
            "path": "file:/Users/noham/Documents/GitHub/Stage-2024/VoTT-v2/sources/2023-100m.mp4",
            "size": {
                "width": 1920,
                "height": 1080
            },
            "state": 1,
            "type": 2
        },
        "timestamp": 0
    },
    "regions": [
        {
            "id": "08w3RqAVd",
            "type": "RECTANGLE",
            "tags": [
                "runner"
            ],
            "boundingBox": {
                "height": 135.5947381422925,
                "width": 105.43921423276501,
                "left": 205.0908080059303,
                "top": 594.3768527667984
            },
            "points": [
                {
                    "x": 205.0908080059303,
                    "y": 594.3768527667984
                },
                {
                    "x": 310.5300222386953,
                    "y": 594.3768527667984
                },
                {
                    "x": 310.5300222386953,
                    "y": 729.9715909090909
                },
                {
                    "x": 205.0908080059303,
                    "y": 729.9715909090909
                }
            ]
        },
        {
            "id": "VsP3qqo-1",
            "type": "RECTANGLE",
            "tags": [
                "runner"
            ],
            "boundingBox": {
                "height": 135.0778162055336,
                "width": 105.72831727205337,
                "left": 346.8180133432172,
                "top": 575.0339673913044
            },
            "points": [
                {
                    "x": 346.8180133432172,
                    "y": 575.0339673913044
                },
                {
                    "x": 452.54633061527056,
                    "y": 575.0339673913044
                },
                {
                    "x": 452.54633061527056,
                    "y": 710.111783596838
                },
                {
                    "x": 346.8180133432172,
                    "y": 710.111783596838
                }
            ]
        },
        {
            "id": "UOES-xmAC",
            "type": "RECTANGLE",
            "tags": [
                "runner"
            ],
            "boundingBox": {
                "height": 135.6836709486166,
                "width": 129.9573758339511,
                "left": 470.26501111934766,
                "top": 570.0092638339921
            },
            "points": [
                {
                    "x": 470.26501111934766,
                    "y": 570.0092638339921
                },
                {
                    "x": 600.2223869532987,
                    "y": 570.0092638339921
                },
                {
                    "x": 600.2223869532987,
                    "y": 705.6929347826087
                },
                {
                    "x": 470.26501111934766,
                    "y": 705.6929347826087
                }
            ]
        },
        {
            "id": "BIEasnHJU",
            "type": "RECTANGLE",
            "tags": [
                "runner"
            ],
            "boundingBox": {
                "height": 128.50234683794466,
                "width": 116.08042994810971,
                "left": 612.7483320978503,
                "top": 561.8552371541502
            },
            "points": [
                {
                    "x": 612.7483320978503,
                    "y": 561.8552371541502
                },
                {
                    "x": 728.82876204596,
                    "y": 561.8552371541502
                },
                {
                    "x": 728.82876204596,
                    "y": 690.3575839920949
                },
                {
                    "x": 612.7483320978503,
                    "y": 690.3575839920949
                }
            ]
        },
        {
            "id": "R_6rOJYub",
            "type": "RECTANGLE",
            "tags": [
                "runner"
            ],
            "boundingBox": {
                "height": 132.37092391304338,
                "width": 111.03780578206079,
                "left": 745.7968865826539,
                "top": 533.596837944664
            },
            "points": [
                {
                    "x": 745.7968865826539,
                    "y": 533.596837944664
                },
                {
                    "x": 856.8346923647147,
                    "y": 533.596837944664
                },
                {
                    "x": 856.8346923647147,
                    "y": 665.9677618577074
                },
                {
                    "x": 745.7968865826539,
                    "y": 665.9677618577074
                }
            ]
        },
        {
            "id": "L348C_UTK",
            "type": "RECTANGLE",
            "tags": [
                "runner"
            ],
            "boundingBox": {
                "height": 120.08152173913044,
                "width": 109.43661971830986,
                "left": 882.5537435137139,
                "top": 536.5649703557312
            },
            "points": [
                {
                    "x": 882.5537435137139,
                    "y": 536.5649703557312
                },
                {
                    "x": 991.9903632320238,
                    "y": 536.5649703557312
                },
                {
                    "x": 991.9903632320238,
                    "y": 656.6464920948616
                },
                {
                    "x": 882.5537435137139,
                    "y": 656.6464920948616
                }
            ]
        },
        {
            "id": "1mGypJkyt",
            "type": "RECTANGLE",
            "tags": [
                "runner"
            ],
            "boundingBox": {
                "height": 133.62154150197628,
                "width": 113.21719792438844,
                "left": 1022.9577464788733,
                "top": 508.3955039525692
            },
            "points": [
                {
                    "x": 1022.9577464788733,
                    "y": 508.3955039525692
                },
                {
                    "x": 1136.1749444032616,
                    "y": 508.3955039525692
                },
                {
                    "x": 1136.1749444032616,
                    "y": 642.0170454545455
                },
                {
                    "x": 1022.9577464788733,
                    "y": 642.0170454545455
                }
            ]
        },
        {
            "id": "J42hmD4Iu",
            "type": "RECTANGLE",
            "tags": [
                "runner"
            ],
            "boundingBox": {
                "height": 128.65797924901185,
                "width": 122.4184581171238,
                "left": 1148.5952557449964,
                "top": 502.65933794466406
            },
            "points": [
                {
                    "x": 1148.5952557449964,
                    "y": 502.65933794466406
                },
                {
                    "x": 1271.01371386212,
                    "y": 502.65933794466406
                },
                {
                    "x": 1271.01371386212,
                    "y": 631.3173171936759
                },
                {
                    "x": 1148.5952557449964,
                    "y": 631.3173171936759
                }
            ]
        }
    ],
    "version": "2.2.0"
}