{
    "asset": {
        "id": "a893492ce464841ecb634be592d37e43",
        "format": "75",
        "state": 2,
        "type": 3,
        "name": "2008-100m.mp4#t=12.75",
        "path": "file:/Users/noham/Documents/GitHub/Stage-2024/VoTT-v2/sources/2008-100m.mp4#t=12.75",
        "size": {
            "width": 1920,
            "height": 1080
        },
        "parent": {
            "format": "mp4",
            "id": "9930a0434ff770117021e970a13029f1",
            "name": "2008-100m.mp4",
            "path": "file:/Users/noham/Documents/GitHub/Stage-2024/VoTT-v2/sources/2008-100m.mp4",
            "size": {
                "width": 1920,
                "height": 1080
            },
            "state": 1,
            "type": 2
        },
        "timestamp": 12.75
    },
    "regions": [
        {
            "id": "1a-zlhOOX",
            "type": "RECTANGLE",
            "tags": [
                "runner"
            ],
            "boundingBox": {
                "height": 265.6632680084746,
                "width": 145.47925608011445,
                "left": 1125.3183118741058,
                "top": 377.4351165254237
            },
            "points": [
                {
                    "x": 1125.3183118741058,
                    "y": 377.4351165254237
                },
                {
                    "x": 1270.7975679542203,
                    "y": 377.4351165254237
                },
                {
                    "x": 1270.7975679542203,
                    "y": 643.0983845338983
                },
                {
                    "x": 1125.3183118741058,
                    "y": 643.0983845338983
                }
            ]
        },
        {
            "id": "-1JV5yBxX",
            "type": "RECTANGLE",
            "tags": [
                "runner"
            ],
            "boundingBox": {
                "height": 250.12897245762713,
                "width": 286.8633762517883,
                "left": 767.4642346208869,
                "top": 685.2394067796611
            },
            "points": [
                {
                    "x": 767.4642346208869,
                    "y": 685.2394067796611
                },
                {
                    "x": 1054.3276108726752,
                    "y": 685.2394067796611
                },
                {
                    "x": 1054.3276108726752,
                    "y": 935.3683792372882
                },
                {
                    "x": 767.4642346208869,
                    "y": 935.3683792372882
                }
            ]
        },
        {
            "id": "axOS7nObu",
            "type": "RECTANGLE",
            "tags": [
                "runner"
            ],
            "boundingBox": {
                "height": 242.61745233050848,
                "width": 188.39413447782547,
                "left": 561.0944206008584,
                "top": 375.5974576271187
            },
            "points": [
                {
                    "x": 561.0944206008584,
                    "y": 375.5974576271187
                },
                {
                    "x": 749.4885550786838,
                    "y": 375.5974576271187
                },
                {
                    "x": 749.4885550786838,
                    "y": 618.2149099576271
                },
                {
                    "x": 561.0944206008584,
                    "y": 618.2149099576271
                }
            ]
        },
        {
            "id": "NXo3AdAH0",
            "type": "RECTANGLE",
            "tags": [
                "runner"
            ],
            "boundingBox": {
                "height": 190.44796080508473,
                "width": 141.81330472103005,
                "left": 683.8841201716738,
                "top": 360.57799258474574
            },
            "points": [
                {
                    "x": 683.8841201716738,
                    "y": 360.57799258474574
                },
                {
                    "x": 825.6974248927039,
                    "y": 360.57799258474574
                },
                {
                    "x": 825.6974248927039,
                    "y": 551.0259533898305
                },
                {
                    "x": 683.8841201716738,
                    "y": 551.0259533898305
                }
            ]
        },
        {
            "id": "O7IjjvFzw",
            "type": "RECTANGLE",
            "tags": [
                "runner"
            ],
            "boundingBox": {
                "height": 292.59891419491527,
                "width": 102.15665236051503,
                "left": 686.81330472103,
                "top": 613.7065677966102
            },
            "points": [
                {
                    "x": 686.81330472103,
                    "y": 613.7065677966102
                },
                {
                    "x": 788.9699570815451,
                    "y": 613.7065677966102
                },
                {
                    "x": 788.9699570815451,
                    "y": 906.3054819915254
                },
                {
                    "x": 686.81330472103,
                    "y": 906.3054819915254
                }
            ]
        },
        {
            "id": "5qIBVmqVg",
            "type": "RECTANGLE",
            "tags": [
                "runner"
            ],
            "boundingBox": {
                "height": 237.79091631355934,
                "width": 123.8555078683834,
                "left": 764.4778254649499,
                "top": 575.9094279661017
            },
            "points": [
                {
                    "x": 764.4778254649499,
                    "y": 575.9094279661017
                },
                {
                    "x": 888.3333333333334,
                    "y": 575.9094279661017
                },
                {
                    "x": 888.3333333333334,
                    "y": 813.7003442796611
                },
                {
                    "x": 764.4778254649499,
                    "y": 813.7003442796611
                }
            ]
        },
        {
            "id": "wUZ-j8PjU",
            "type": "RECTANGLE",
            "tags": [
                "runner"
            ],
            "boundingBox": {
                "height": 227.71239406779662,
                "width": 159.7997138769672,
                "left": 843.1902718168814,
                "top": 461.2881355932203
            },
            "points": [
                {
                    "x": 843.1902718168814,
                    "y": 461.2881355932203
                },
                {
                    "x": 1002.9899856938486,
                    "y": 461.2881355932203
                },
                {
                    "x": 1002.9899856938486,
                    "y": 689.0005296610169
                },
                {
                    "x": 843.1902718168814,
                    "y": 689.0005296610169
                }
            ]
        }
    ],
    "version": "2.2.0"
}