{
    "asset": {
        "id": "db1f71d6f0694310af0a1276a1c88dad",
        "format": "5",
        "state": 2,
        "type": 3,
        "name": "2008-100m.mp4#t=11.5",
        "path": "file:/Users/noham/Documents/GitHub/Stage-2024/VoTT-v2/sources/2008-100m.mp4#t=11.5",
        "size": {
            "width": 1920,
            "height": 1080
        },
        "parent": {
            "format": "mp4",
            "id": "9930a0434ff770117021e970a13029f1",
            "name": "2008-100m.mp4",
            "path": "file:/Users/noham/Documents/GitHub/Stage-2024/VoTT-v2/sources/2008-100m.mp4",
            "size": {
                "width": 1920,
                "height": 1080
            },
            "state": 1,
            "type": 2
        },
        "timestamp": 11.5
    },
    "regions": [
        {
            "id": "g-if7GXgv",
            "type": "RECTANGLE",
            "tags": [
                "runner"
            ],
            "boundingBox": {
                "height": 247.47259004237287,
                "width": 78.05436337625169,
                "left": 584.8354792560802,
                "top": 640.3204449152543
            },
            "points": [
                {
                    "x": 584.8354792560802,
                    "y": 640.3204449152543
                },
                {
                    "x": 662.8898426323319,
                    "y": 640.3204449152543
                },
                {
                    "x": 662.8898426323319,
                    "y": 887.7930349576271
                },
                {
                    "x": 584.8354792560802,
                    "y": 887.7930349576271
                }
            ]
        },
        {
            "id": "RQHVcoyYX",
            "type": "RECTANGLE",
            "tags": [
                "runner"
            ],
            "boundingBox": {
                "height": 235.21676377118644,
                "width": 138.6552217453505,
                "left": 708.7804005722461,
                "top": 544.869438559322
            },
            "points": [
                {
                    "x": 708.7804005722461,
                    "y": 544.869438559322
                },
                {
                    "x": 847.4356223175965,
                    "y": 544.869438559322
                },
                {
                    "x": 847.4356223175965,
                    "y": 780.0862023305085
                },
                {
                    "x": 708.7804005722461,
                    "y": 780.0862023305085
                }
            ]
        },
        {
            "id": "nA9nqIsJu",
            "type": "RECTANGLE",
            "tags": [
                "runner"
            ],
            "boundingBox": {
                "height": 224.10500529661016,
                "width": 110.22889842632331,
                "left": 911.0336194563662,
                "top": 474.73093220338984
            },
            "points": [
                {
                    "x": 911.0336194563662,
                    "y": 474.73093220338984
                },
                {
                    "x": 1021.2625178826895,
                    "y": 474.73093220338984
                },
                {
                    "x": 1021.2625178826895,
                    "y": 698.8359375
                },
                {
                    "x": 911.0336194563662,
                    "y": 698.8359375
                }
            ]
        },
        {
            "id": "Q7Yr9ZYy1",
            "type": "RECTANGLE",
            "tags": [
                "runner"
            ],
            "boundingBox": {
                "height": 234.3050847457627,
                "width": 146.84907010014305,
                "left": 1217.038626609442,
                "top": 433.76257944915255
            },
            "points": [
                {
                    "x": 1217.038626609442,
                    "y": 433.76257944915255
                },
                {
                    "x": 1363.887696709585,
                    "y": 433.76257944915255
                },
                {
                    "x": 1363.887696709585,
                    "y": 668.0676641949152
                },
                {
                    "x": 1217.038626609442,
                    "y": 668.0676641949152
                }
            ]
        },
        {
            "id": "5S7-x4q-B",
            "type": "RECTANGLE",
            "tags": [
                "runner"
            ],
            "boundingBox": {
                "height": 193.5869968220339,
                "width": 128.80185979971387,
                "left": 952.9577968526467,
                "top": 368.5721663135593
            },
            "points": [
                {
                    "x": 952.9577968526467,
                    "y": 368.5721663135593
                },
                {
                    "x": 1081.7596566523605,
                    "y": 368.5721663135593
                },
                {
                    "x": 1081.7596566523605,
                    "y": 562.1591631355932
                },
                {
                    "x": 952.9577968526467,
                    "y": 562.1591631355932
                }
            ]
        },
        {
            "id": "jd-pJ_vKA",
            "type": "RECTANGLE",
            "tags": [
                "runner"
            ],
            "boundingBox": {
                "height": 199.37526483050848,
                "width": 151.65951359084406,
                "left": 773.683834048641,
                "top": 371.7648305084746
            },
            "points": [
                {
                    "x": 773.683834048641,
                    "y": 371.7648305084746
                },
                {
                    "x": 925.3433476394849,
                    "y": 371.7648305084746
                },
                {
                    "x": 925.3433476394849,
                    "y": 571.1400953389831
                },
                {
                    "x": 773.683834048641,
                    "y": 571.1400953389831
                }
            ]
        },
        {
            "id": "QtfnGbr5x",
            "type": "RECTANGLE",
            "tags": [
                "runner"
            ],
            "boundingBox": {
                "height": 234.34798728813558,
                "width": 95.51502145922747,
                "left": 802.049356223176,
                "top": 527.4796080508474
            },
            "points": [
                {
                    "x": 802.049356223176,
                    "y": 527.4796080508474
                },
                {
                    "x": 897.5643776824035,
                    "y": 527.4796080508474
                },
                {
                    "x": 897.5643776824035,
                    "y": 761.8275953389831
                },
                {
                    "x": 802.049356223176,
                    "y": 761.8275953389831
                }
            ]
        }
    ],
    "version": "2.2.0"
}