{
    "asset": {
        "id": "f2645ca95a19856b18a01cd2580e6958",
        "format": "25",
        "state": 2,
        "type": 3,
        "name": "2012-100m.mp4#t=15.25",
        "path": "file:/Users/noham/Documents/GitHub/Stage-2024/VoTT-v2/sources/2012-100m.mp4#t=15.25",
        "size": {
            "width": 1280,
            "height": 720
        },
        "parent": {
            "format": "mp4",
            "id": "562ca98225d5d705bc4a6fe23a06daae",
            "name": "2012-100m.mp4",
            "path": "file:/Users/noham/Documents/GitHub/Stage-2024/VoTT-v2/sources/2012-100m.mp4",
            "size": {
                "width": 1280,
                "height": 720
            },
            "state": 1,
            "type": 2
        },
        "timestamp": 15.25
    },
    "regions": [
        {
            "id": "LmUEKkpDq",
            "type": "RECTANGLE",
            "tags": [
                "runner"
            ],
            "boundingBox": {
                "height": 160.25768008474577,
                "width": 61.78826895565093,
                "left": 744.3276108726752,
                "top": 335.4788135593221
            },
            "points": [
                {
                    "x": 744.3276108726752,
                    "y": 335.4788135593221
                },
                {
                    "x": 806.1158798283261,
                    "y": 335.4788135593221
                },
                {
                    "x": 806.1158798283261,
                    "y": 495.7364936440678
                },
                {
                    "x": 744.3276108726752,
                    "y": 495.7364936440678
                }
            ]
        },
        {
            "id": "xEe597BUW",
            "type": "RECTANGLE",
            "tags": [
                "runner"
            ],
            "boundingBox": {
                "height": 137.55985169491527,
                "width": 44.380066762041146,
                "left": 593.4835479256078,
                "top": 291.66101694915255
            },
            "points": [
                {
                    "x": 593.4835479256078,
                    "y": 291.66101694915255
                },
                {
                    "x": 637.863614687649,
                    "y": 291.66101694915255
                },
                {
                    "x": 637.863614687649,
                    "y": 429.2208686440678
                },
                {
                    "x": 593.4835479256078,
                    "y": 429.2208686440678
                }
            ]
        },
        {
            "id": "L9xQXFXE8",
            "type": "RECTANGLE",
            "tags": [
                "runner"
            ],
            "boundingBox": {
                "height": 131.23887711864407,
                "width": 112.02908917501192,
                "left": 285.6485455412494,
                "top": 245.28813559322035
            },
            "points": [
                {
                    "x": 285.6485455412494,
                    "y": 245.28813559322035
                },
                {
                    "x": 397.6776347162613,
                    "y": 245.28813559322035
                },
                {
                    "x": 397.6776347162613,
                    "y": 376.5270127118644
                },
                {
                    "x": 285.6485455412494,
                    "y": 376.5270127118644
                }
            ]
        },
        {
            "id": "oCZreTUns",
            "type": "RECTANGLE",
            "tags": [
                "runner"
            ],
            "boundingBox": {
                "height": 148.0638241525424,
                "width": 128.688602765856,
                "left": 444.0701001430615,
                "top": 435.4250529661017
            },
            "points": [
                {
                    "x": 444.0701001430615,
                    "y": 435.4250529661017
                },
                {
                    "x": 572.7587029089175,
                    "y": 435.4250529661017
                },
                {
                    "x": 572.7587029089175,
                    "y": 583.4888771186442
                },
                {
                    "x": 444.0701001430615,
                    "y": 583.4888771186442
                }
            ]
        },
        {
            "id": "mIn17zkd4",
            "type": "RECTANGLE",
            "tags": [
                "runner"
            ],
            "boundingBox": {
                "height": 145.16075211864407,
                "width": 105.81068192656174,
                "left": 518.0948974725799,
                "top": 380.20471398305085
            },
            "points": [
                {
                    "x": 518.0948974725799,
                    "y": 380.20471398305085
                },
                {
                    "x": 623.9055793991416,
                    "y": 380.20471398305085
                },
                {
                    "x": 623.9055793991416,
                    "y": 525.365466101695
                },
                {
                    "x": 518.0948974725799,
                    "y": 525.365466101695
                }
            ]
        },
        {
            "id": "YbyePu8iO",
            "type": "RECTANGLE",
            "tags": [
                "runner"
            ],
            "boundingBox": {
                "height": 121.38559322033899,
                "width": 84.15832141154029,
                "left": 482.63471626132565,
                "top": 332.3445444915254
            },
            "points": [
                {
                    "x": 482.63471626132565,
                    "y": 332.3445444915254
                },
                {
                    "x": 566.7930376728659,
                    "y": 332.3445444915254
                },
                {
                    "x": 566.7930376728659,
                    "y": 453.7301377118644
                },
                {
                    "x": 482.63471626132565,
                    "y": 453.7301377118644
                }
            ]
        },
        {
            "id": "yXTJynwjC",
            "type": "RECTANGLE",
            "tags": [
                "runner"
            ],
            "boundingBox": {
                "height": 105.10646186440678,
                "width": 50.193133047210296,
                "left": 502.20076299475437,
                "top": 288.14777542372883
            },
            "points": [
                {
                    "x": 502.20076299475437,
                    "y": 288.14777542372883
                },
                {
                    "x": 552.3938960419647,
                    "y": 288.14777542372883
                },
                {
                    "x": 552.3938960419647,
                    "y": 393.25423728813564
                },
                {
                    "x": 502.20076299475437,
                    "y": 393.25423728813564
                }
            ]
        }
    ],
    "version": "2.2.0"
}