{
    "asset": {
        "id": "f774658c2d79267232411d910345786b",
        "format": "25",
        "state": 2,
        "type": 3,
        "name": "2008-200m.mp4#t=13.25",
        "path": "file:/Users/noham/Documents/GitHub/Stage-2024/VoTT-v2/sources/2008-200m.mp4#t=13.25",
        "size": {
            "width": 1920,
            "height": 1080
        },
        "parent": {
            "format": "mp4",
            "id": "b8b1fa7f0e63eb7f472ff8f2ce876910",
            "name": "2008-200m.mp4",
            "path": "file:/Users/noham/Documents/GitHub/Stage-2024/VoTT-v2/sources/2008-200m.mp4",
            "size": {
                "width": 1920,
                "height": 1080
            },
            "state": 1,
            "type": 2
        },
        "timestamp": 13.25
    },
    "regions": [
        {
            "id": "mRmqa7d7K",
            "type": "RECTANGLE",
            "tags": [
                "runner"
            ],
            "boundingBox": {
                "height": 253.2787341101695,
                "width": 112.52861230329042,
                "left": 122.0958512160229,
                "top": 375.7297404661017
            },
            "points": [
                {
                    "x": 122.0958512160229,
                    "y": 375.7297404661017
                },
                {
                    "x": 234.6244635193133,
                    "y": 375.7297404661017
                },
                {
                    "x": 234.6244635193133,
                    "y": 629.0084745762712
                },
                {
                    "x": 122.0958512160229,
                    "y": 629.0084745762712
                }
            ]
        },
        {
            "id": "T7rNnTxEG",
            "type": "RECTANGLE",
            "tags": [
                "runner"
            ],
            "boundingBox": {
                "height": 244.80905720338984,
                "width": 119.62804005722461,
                "left": 337.25321888412014,
                "top": 439.8011122881356
            },
            "points": [
                {
                    "x": 337.25321888412014,
                    "y": 439.8011122881356
                },
                {
                    "x": 456.88125894134475,
                    "y": 439.8011122881356
                },
                {
                    "x": 456.88125894134475,
                    "y": 684.6101694915254
                },
                {
                    "x": 337.25321888412014,
                    "y": 684.6101694915254
                }
            ]
        },
        {
            "id": "CqfGocrb_",
            "type": "RECTANGLE",
            "tags": [
                "runner"
            ],
            "boundingBox": {
                "height": 245.86731991525423,
                "width": 124.32045779685265,
                "left": 482.8934191702432,
                "top": 390.24510063559325
            },
            "points": [
                {
                    "x": 482.8934191702432,
                    "y": 390.24510063559325
                },
                {
                    "x": 607.2138769670959,
                    "y": 390.24510063559325
                },
                {
                    "x": 607.2138769670959,
                    "y": 636.1124205508474
                },
                {
                    "x": 482.8934191702432,
                    "y": 636.1124205508474
                }
            ]
        },
        {
            "id": "gEya4LFz1",
            "type": "RECTANGLE",
            "tags": [
                "runner"
            ],
            "boundingBox": {
                "height": 223.9584216101695,
                "width": 91.01931330472102,
                "left": 618.9556509298999,
                "top": 320.5320444915254
            },
            "points": [
                {
                    "x": 618.9556509298999,
                    "y": 320.5320444915254
                },
                {
                    "x": 709.9749642346209,
                    "y": 320.5320444915254
                },
                {
                    "x": 709.9749642346209,
                    "y": 544.4904661016949
                },
                {
                    "x": 618.9556509298999,
                    "y": 544.4904661016949
                }
            ]
        },
        {
            "id": "hACM0kk5u",
            "type": "RECTANGLE",
            "tags": [
                "runner"
            ],
            "boundingBox": {
                "height": 286.78561970338984,
                "width": 95.11444921316166,
                "left": 895.2181688125894,
                "top": 387.15969279661016
            },
            "points": [
                {
                    "x": 895.2181688125894,
                    "y": 387.15969279661016
                },
                {
                    "x": 990.3326180257511,
                    "y": 387.15969279661016
                },
                {
                    "x": 990.3326180257511,
                    "y": 673.9453125
                },
                {
                    "x": 895.2181688125894,
                    "y": 673.9453125
                }
            ]
        },
        {
            "id": "rOg1pmF7W",
            "type": "RECTANGLE",
            "tags": [
                "runner"
            ],
            "boundingBox": {
                "height": 221.9598781779661,
                "width": 98.69098712446352,
                "left": 951.8562231759656,
                "top": 293.82878707627117
            },
            "points": [
                {
                    "x": 951.8562231759656,
                    "y": 293.82878707627117
                },
                {
                    "x": 1050.5472103004292,
                    "y": 293.82878707627117
                },
                {
                    "x": 1050.5472103004292,
                    "y": 515.7886652542373
                },
                {
                    "x": 951.8562231759656,
                    "y": 515.7886652542373
                }
            ]
        },
        {
            "id": "eBx2683Xy",
            "type": "RECTANGLE",
            "tags": [
                "runner"
            ],
            "boundingBox": {
                "height": 233.58289194915255,
                "width": 102.19599427753934,
                "left": 1034.9284692417739,
                "top": 176.0756091101695
            },
            "points": [
                {
                    "x": 1034.9284692417739,
                    "y": 176.0756091101695
                },
                {
                    "x": 1137.1244635193134,
                    "y": 176.0756091101695
                },
                {
                    "x": 1137.1244635193134,
                    "y": 409.658501059322
                },
                {
                    "x": 1034.9284692417739,
                    "y": 409.658501059322
                }
            ]
        },
        {
            "id": "JYFgSCdly",
            "type": "RECTANGLE",
            "tags": [
                "runner"
            ],
            "boundingBox": {
                "height": 238.74192266949152,
                "width": 106.30901287553648,
                "left": 1210.6008583690987,
                "top": 151.760593220339
            },
            "points": [
                {
                    "x": 1210.6008583690987,
                    "y": 151.760593220339
                },
                {
                    "x": 1316.9098712446353,
                    "y": 151.760593220339
                },
                {
                    "x": 1316.9098712446353,
                    "y": 390.50251588983053
                },
                {
                    "x": 1210.6008583690987,
                    "y": 390.50251588983053
                }
            ]
        }
    ],
    "version": "2.2.0"
}