{
    "asset": {
        "id": "fa9cd9d5778c6013ccbd37b715d37293",
        "format": "mp4",
        "state": 2,
        "type": 3,
        "name": "2020-100m-m.mp4#t=0",
        "path": "file:/Users/noham/Documents/GitHub/Stage-2024/VoTT-v2/sources/2020-100m-m.mp4#t=0",
        "size": {
            "width": 1920,
            "height": 1080
        },
        "parent": {
            "format": "mp4",
            "id": "428173b682a54a335d7df96068606865",
            "name": "2020-100m-m.mp4",
            "path": "file:/Users/noham/Documents/GitHub/Stage-2024/VoTT-v2/sources/2020-100m-m.mp4",
            "size": {
                "width": 1920,
                "height": 1080
            },
            "state": 1,
            "type": 2
        },
        "timestamp": 0
    },
    "regions": [
        {
            "id": "4CaMJOu1W",
            "type": "RECTANGLE",
            "tags": [
                "runner"
            ],
            "boundingBox": {
                "height": 167.96072134387353,
                "width": 127.67234988880652,
                "left": 242.29614529280948,
                "top": 409.15205039525694
            },
            "points": [
                {
                    "x": 242.29614529280948,
                    "y": 409.15205039525694
                },
                {
                    "x": 369.96849518161605,
                    "y": 409.15205039525694
                },
                {
                    "x": 369.96849518161605,
                    "y": 577.1127717391304
                },
                {
                    "x": 242.29614529280948,
                    "y": 577.1127717391304
                }
            ]
        },
        {
            "id": "NQHL2Y_P6",
            "type": "RECTANGLE",
            "tags": [
                "runner"
            ],
            "boundingBox": {
                "height": 147.30051877470356,
                "width": 113.03372868791698,
                "left": 434.4718309859156,
                "top": 419.7628458498024
            },
            "points": [
                {
                    "x": 434.4718309859156,
                    "y": 419.7628458498024
                },
                {
                    "x": 547.5055596738325,
                    "y": 419.7628458498024
                },
                {
                    "x": 547.5055596738325,
                    "y": 567.0633646245059
                },
                {
                    "x": 434.4718309859156,
                    "y": 567.0633646245059
                }
            ]
        },
        {
            "id": "uY8m63LhY",
            "type": "RECTANGLE",
            "tags": [
                "runner"
            ],
            "boundingBox": {
                "height": 143.4875247035573,
                "width": 120.99518161601186,
                "left": 607.7223869532987,
                "top": 414.77705039525694
            },
            "points": [
                {
                    "x": 607.7223869532987,
                    "y": 414.77705039525694
                },
                {
                    "x": 728.7175685693106,
                    "y": 414.77705039525694
                },
                {
                    "x": 728.7175685693106,
                    "y": 558.2645750988142
                },
                {
                    "x": 607.7223869532987,
                    "y": 558.2645750988142
                }
            ]
        },
        {
            "id": "21j7QjJ9s",
            "type": "RECTANGLE",
            "tags": [
                "runner"
            ],
            "boundingBox": {
                "height": 142.27025691699606,
                "width": 119.02149740548555,
                "left": 789.9462564862862,
                "top": 414.9326828063241
            },
            "points": [
                {
                    "x": 789.9462564862862,
                    "y": 414.9326828063241
                },
                {
                    "x": 908.9677538917717,
                    "y": 414.9326828063241
                },
                {
                    "x": 908.9677538917717,
                    "y": 557.2029397233201
                },
                {
                    "x": 789.9462564862862,
                    "y": 557.2029397233201
                }
            ]
        },
        {
            "id": "E5ROXtDBP",
            "type": "RECTANGLE",
            "tags": [
                "runner"
            ],
            "boundingBox": {
                "height": 167.57719861660078,
                "width": 133.47664936990364,
                "left": 955.4633061527057,
                "top": 381.7940958498024
            },
            "points": [
                {
                    "x": 955.4633061527057,
                    "y": 381.7940958498024
                },
                {
                    "x": 1088.9399555226094,
                    "y": 381.7940958498024
                },
                {
                    "x": 1088.9399555226094,
                    "y": 549.3712944664031
                },
                {
                    "x": 955.4633061527057,
                    "y": 549.3712944664031
                }
            ]
        },
        {
            "id": "EaGWeibou",
            "type": "RECTANGLE",
            "tags": [
                "runner"
            ],
            "boundingBox": {
                "height": 169.05014822134387,
                "width": 140.65418828762046,
                "left": 1287.0144551519645,
                "top": 362.8736413043478
            },
            "points": [
                {
                    "x": 1287.0144551519645,
                    "y": 362.8736413043478
                },
                {
                    "x": 1427.668643439585,
                    "y": 362.8736413043478
                },
                {
                    "x": 1427.668643439585,
                    "y": 531.9237895256917
                },
                {
                    "x": 1287.0144551519645,
                    "y": 531.9237895256917
                }
            ]
        },
        {
            "id": "KtumP72Sy",
            "type": "RECTANGLE",
            "tags": [
                "runner"
            ],
            "boundingBox": {
                "height": 153.33683300395256,
                "width": 124.55893254262418,
                "left": 1474.6367679762789,
                "top": 374.4349061264822
            },
            "points": [
                {
                    "x": 1474.6367679762789,
                    "y": 374.4349061264822
                },
                {
                    "x": 1599.1957005189029,
                    "y": 374.4349061264822
                },
                {
                    "x": 1599.1957005189029,
                    "y": 527.7717391304348
                },
                {
                    "x": 1474.6367679762789,
                    "y": 527.7717391304348
                }
            ]
        }
    ],
    "version": "2.2.0"
}